{
  "A": [
    {
      "date": "2026-06-11",
      "round": "Matchday 1",
      "ground": "Mexico City",
      "team1": "Mexico",
      "team2": "South Africa",
      "team1_flag": "🇲🇽",
      "team2_flag": "🇿🇦",
      "t1_win": 0.5681,
      "draw": 0.2729,
      "t2_win": 0.159
    },
    {
      "date": "2026-06-11",
      "round": "Matchday 1",
      "ground": "Guadalajara (Zapopan)",
      "team1": "South Korea",
      "team2": "Czech Republic",
      "team1_flag": "🇰🇷",
      "team2_flag": "🇨🇿",
      "t1_win": 0.3143,
      "draw": 0.2939,
      "t2_win": 0.3918
    },
    {
      "date": "2026-06-18",
      "round": "Matchday 8",
      "ground": "Atlanta",
      "team1": "Czech Republic",
      "team2": "South Africa",
      "team1_flag": "🇨🇿",
      "team2_flag": "🇿🇦",
      "t1_win": 0.4859,
      "draw": 0.3059,
      "t2_win": 0.2082
    },
    {
      "date": "2026-06-18",
      "round": "Matchday 8",
      "ground": "Guadalajara (Zapopan)",
      "team1": "Mexico",
      "team2": "South Korea",
      "team1_flag": "🇲🇽",
      "team2_flag": "🇰🇷",
      "t1_win": 0.5002,
      "draw": 0.3018,
      "t2_win": 0.198
    },
    {
      "date": "2026-06-24",
      "round": "Matchday 14",
      "ground": "Mexico City",
      "team1": "Czech Republic",
      "team2": "Mexico",
      "team1_flag": "🇨🇿",
      "team2_flag": "🇲🇽",
      "t1_win": 0.2805,
      "draw": 0.2803,
      "t2_win": 0.4392
    },
    {
      "date": "2026-06-24",
      "round": "Matchday 14",
      "ground": "Monterrey (Guadalupe)",
      "team1": "South Africa",
      "team2": "South Korea",
      "team1_flag": "🇿🇦",
      "team2_flag": "🇰🇷",
      "t1_win": 0.2567,
      "draw": 0.3337,
      "t2_win": 0.4096
    }
  ],
  "B": [
    {
      "date": "2026-06-12",
      "round": "Matchday 2",
      "ground": "Toronto",
      "team1": "Canada",
      "team2": "Bosnia and Herzegovina",
      "team1_flag": "🇨🇦",
      "team2_flag": "🇧🇦",
      "t1_win": 0.4746,
      "draw": 0.2651,
      "t2_win": 0.2603
    },
    {
      "date": "2026-06-13",
      "round": "Matchday 3",
      "ground": "San Francisco Bay Area (Santa Clara)",
      "team1": "Qatar",
      "team2": "Switzerland",
      "team1_flag": "🇶🇦",
      "team2_flag": "🇨🇭",
      "t1_win": 0.0952,
      "draw": 0.1958,
      "t2_win": 0.709
    },
    {
      "date": "2026-06-18",
      "round": "Matchday 8",
      "ground": "Los Angeles (Inglewood)",
      "team1": "Switzerland",
      "team2": "Bosnia and Herzegovina",
      "team1_flag": "🇨🇭",
      "team2_flag": "🇧🇦",
      "t1_win": 0.5915,
      "draw": 0.2424,
      "t2_win": 0.1661
    },
    {
      "date": "2026-06-18",
      "round": "Matchday 8",
      "ground": "Vancouver",
      "team1": "Canada",
      "team2": "Qatar",
      "team1_flag": "🇨🇦",
      "team2_flag": "🇶🇦",
      "t1_win": 0.5877,
      "draw": 0.2485,
      "t2_win": 0.1638
    },
    {
      "date": "2026-06-24",
      "round": "Matchday 14",
      "ground": "Vancouver",
      "team1": "Switzerland",
      "team2": "Canada",
      "team1_flag": "🇨🇭",
      "team2_flag": "🇨🇦",
      "t1_win": 0.4615,
      "draw": 0.286,
      "t2_win": 0.2526
    },
    {
      "date": "2026-06-24",
      "round": "Matchday 14",
      "ground": "Seattle",
      "team1": "Bosnia and Herzegovina",
      "team2": "Qatar",
      "team1_flag": "🇧🇦",
      "team2_flag": "🇶🇦",
      "t1_win": 0.4763,
      "draw": 0.2889,
      "t2_win": 0.2347
    }
  ],
  "C": [
    {
      "date": "2026-06-13",
      "round": "Matchday 3",
      "ground": "New York/New Jersey (East Rutherford)",
      "team1": "Brazil",
      "team2": "Morocco",
      "team1_flag": "🇧🇷",
      "team2_flag": "🇲🇦",
      "t1_win": 0.5315,
      "draw": 0.2831,
      "t2_win": 0.1855
    },
    {
      "date": "2026-06-13",
      "round": "Matchday 3",
      "ground": "Boston (Foxborough)",
      "team1": "Haiti",
      "team2": "Scotland",
      "team1_flag": "🇭🇹",
      "team2_flag": "🏴󠁧󠁢󠁳󠁣󠁴󠁿",
      "t1_win": 0.1241,
      "draw": 0.207,
      "t2_win": 0.669
    },
    {
      "date": "2026-06-19",
      "round": "Matchday 9",
      "ground": "Boston (Foxborough)",
      "team1": "Scotland",
      "team2": "Morocco",
      "team1_flag": "🏴󠁧󠁢󠁳󠁣󠁴󠁿",
      "team2_flag": "🇲🇦",
      "t1_win": 0.263,
      "draw": 0.2989,
      "t2_win": 0.4381
    },
    {
      "date": "2026-06-19",
      "round": "Matchday 9",
      "ground": "Philadelphia",
      "team1": "Brazil",
      "team2": "Haiti",
      "team1_flag": "🇧🇷",
      "team2_flag": "🇭🇹",
      "t1_win": 0.8617,
      "draw": 0.097,
      "t2_win": 0.0412
    },
    {
      "date": "2026-06-24",
      "round": "Matchday 14",
      "ground": "Miami (Miami Gardens)",
      "team1": "Scotland",
      "team2": "Brazil",
      "team1_flag": "🏴󠁧󠁢󠁳󠁣󠁴󠁿",
      "team2_flag": "🇧🇷",
      "t1_win": 0.1514,
      "draw": 0.2284,
      "t2_win": 0.6202
    },
    {
      "date": "2026-06-24",
      "round": "Matchday 14",
      "ground": "Atlanta",
      "team1": "Morocco",
      "team2": "Haiti",
      "team1_flag": "🇲🇦",
      "team2_flag": "🇭🇹",
      "t1_win": 0.6838,
      "draw": 0.2254,
      "t2_win": 0.0908
    }
  ],
  "D": [
    {
      "date": "2026-06-12",
      "round": "Matchday 2",
      "ground": "Los Angeles (Inglewood)",
      "team1": "United States",
      "team2": "Paraguay",
      "team1_flag": "🇺🇸",
      "team2_flag": "🇵🇾",
      "t1_win": 0.3692,
      "draw": 0.2959,
      "t2_win": 0.3349
    },
    {
      "date": "2026-06-13",
      "round": "Matchday 3",
      "ground": "Vancouver",
      "team1": "Australia",
      "team2": "Turkey",
      "team1_flag": "🇦🇺",
      "team2_flag": "🇹🇷",
      "t1_win": 0.3527,
      "draw": 0.3162,
      "t2_win": 0.3311
    },
    {
      "date": "2026-06-19",
      "round": "Matchday 9",
      "ground": "Seattle",
      "team1": "United States",
      "team2": "Australia",
      "team1_flag": "🇺🇸",
      "team2_flag": "🇦🇺",
      "t1_win": 0.3739,
      "draw": 0.3191,
      "t2_win": 0.307
    },
    {
      "date": "2026-06-19",
      "round": "Matchday 9",
      "ground": "San Francisco Bay Area (Santa Clara)",
      "team1": "Turkey",
      "team2": "Paraguay",
      "team1_flag": "🇹🇷",
      "team2_flag": "🇵🇾",
      "t1_win": 0.2984,
      "draw": 0.3137,
      "t2_win": 0.3879
    },
    {
      "date": "2026-06-25",
      "round": "Matchday 15",
      "ground": "Los Angeles (Inglewood)",
      "team1": "Turkey",
      "team2": "United States",
      "team1_flag": "🇹🇷",
      "team2_flag": "🇺🇸",
      "t1_win": 0.3123,
      "draw": 0.3084,
      "t2_win": 0.3794
    },
    {
      "date": "2026-06-25",
      "round": "Matchday 15",
      "ground": "San Francisco Bay Area (Santa Clara)",
      "team1": "Paraguay",
      "team2": "Australia",
      "team1_flag": "🇵🇾",
      "team2_flag": "🇦🇺",
      "t1_win": 0.3522,
      "draw": 0.3134,
      "t2_win": 0.3344
    }
  ],
  "E": [
    {
      "date": "2026-06-14",
      "round": "Matchday 4",
      "ground": "Houston",
      "team1": "Germany",
      "team2": "Curacao",
      "team1_flag": "🇩🇪",
      "team2_flag": "🇨🇼",
      "t1_win": 0.8929,
      "draw": 0.0732,
      "t2_win": 0.034
    },
    {
      "date": "2026-06-14",
      "round": "Matchday 4",
      "ground": "Philadelphia",
      "team1": "Ivory Coast",
      "team2": "Ecuador",
      "team1_flag": "🇨🇮",
      "team2_flag": "🇪🇨",
      "t1_win": 0.3083,
      "draw": 0.2997,
      "t2_win": 0.392
    },
    {
      "date": "2026-06-20",
      "round": "Matchday 10",
      "ground": "Toronto",
      "team1": "Germany",
      "team2": "Ivory Coast",
      "team1_flag": "🇩🇪",
      "team2_flag": "🇨🇮",
      "t1_win": 0.6149,
      "draw": 0.2244,
      "t2_win": 0.1607
    },
    {
      "date": "2026-06-20",
      "round": "Matchday 10",
      "ground": "Kansas City",
      "team1": "Ecuador",
      "team2": "Curacao",
      "team1_flag": "🇪🇨",
      "team2_flag": "🇨🇼",
      "t1_win": 0.7394,
      "draw": 0.1789,
      "t2_win": 0.0818
    },
    {
      "date": "2026-06-25",
      "round": "Matchday 15",
      "ground": "Philadelphia",
      "team1": "Curacao",
      "team2": "Ivory Coast",
      "team1_flag": "🇨🇼",
      "team2_flag": "🇨🇮",
      "t1_win": 0.0836,
      "draw": 0.1715,
      "t2_win": 0.7448
    },
    {
      "date": "2026-06-25",
      "round": "Matchday 15",
      "ground": "New York/New Jersey (East Rutherford)",
      "team1": "Ecuador",
      "team2": "Germany",
      "team1_flag": "🇪🇨",
      "team2_flag": "🇩🇪",
      "t1_win": 0.1873,
      "draw": 0.2243,
      "t2_win": 0.5884
    }
  ],
  "F": [
    {
      "date": "2026-06-14",
      "round": "Matchday 4",
      "ground": "Dallas (Arlington)",
      "team1": "Netherlands",
      "team2": "Japan",
      "team1_flag": "🇳🇱",
      "team2_flag": "🇯🇵",
      "t1_win": 0.5708,
      "draw": 0.2496,
      "t2_win": 0.1796
    },
    {
      "date": "2026-06-14",
      "round": "Matchday 4",
      "ground": "Monterrey (Guadalupe)",
      "team1": "Sweden",
      "team2": "Tunisia",
      "team1_flag": "🇸🇪",
      "team2_flag": "🇹🇳",
      "t1_win": 0.556,
      "draw": 0.2558,
      "t2_win": 0.1883
    },
    {
      "date": "2026-06-20",
      "round": "Matchday 10",
      "ground": "Houston",
      "team1": "Netherlands",
      "team2": "Sweden",
      "team1_flag": "🇳🇱",
      "team2_flag": "🇸🇪",
      "t1_win": 0.5587,
      "draw": 0.242,
      "t2_win": 0.1993
    },
    {
      "date": "2026-06-20",
      "round": "Matchday 10",
      "ground": "Monterrey (Guadalupe)",
      "team1": "Tunisia",
      "team2": "Japan",
      "team1_flag": "🇹🇳",
      "team2_flag": "🇯🇵",
      "t1_win": 0.2263,
      "draw": 0.2627,
      "t2_win": 0.5111
    },
    {
      "date": "2026-06-25",
      "round": "Matchday 15",
      "ground": "Dallas (Arlington)",
      "team1": "Japan",
      "team2": "Sweden",
      "team1_flag": "🇯🇵",
      "team2_flag": "🇸🇪",
      "t1_win": 0.3582,
      "draw": 0.2501,
      "t2_win": 0.3918
    },
    {
      "date": "2026-06-25",
      "round": "Matchday 15",
      "ground": "Kansas City",
      "team1": "Tunisia",
      "team2": "Netherlands",
      "team1_flag": "🇹🇳",
      "team2_flag": "🇳🇱",
      "t1_win": 0.1048,
      "draw": 0.2048,
      "t2_win": 0.6904
    }
  ],
  "G": [
    {
      "date": "2026-06-15",
      "round": "Matchday 5",
      "ground": "Seattle",
      "team1": "Belgium",
      "team2": "Egypt",
      "team1_flag": "🇧🇪",
      "team2_flag": "🇪🇬",
      "t1_win": 0.5153,
      "draw": 0.2798,
      "t2_win": 0.2049
    },
    {
      "date": "2026-06-15",
      "round": "Matchday 5",
      "ground": "Los Angeles (Inglewood)",
      "team1": "Iran",
      "team2": "New Zealand",
      "team1_flag": "🇮🇷",
      "team2_flag": "🇳🇿",
      "t1_win": 0.5998,
      "draw": 0.2547,
      "t2_win": 0.1455
    },
    {
      "date": "2026-06-21",
      "round": "Matchday 11",
      "ground": "Los Angeles (Inglewood)",
      "team1": "Belgium",
      "team2": "Iran",
      "team1_flag": "🇧🇪",
      "team2_flag": "🇮🇷",
      "t1_win": 0.4571,
      "draw": 0.3014,
      "t2_win": 0.2415
    },
    {
      "date": "2026-06-21",
      "round": "Matchday 11",
      "ground": "Vancouver",
      "team1": "New Zealand",
      "team2": "Egypt",
      "team1_flag": "🇳🇿",
      "team2_flag": "🇪🇬",
      "t1_win": 0.1691,
      "draw": 0.2661,
      "t2_win": 0.5648
    },
    {
      "date": "2026-06-26",
      "round": "Matchday 16",
      "ground": "Seattle",
      "team1": "Egypt",
      "team2": "Iran",
      "team1_flag": "🇪🇬",
      "team2_flag": "🇮🇷",
      "t1_win": 0.2776,
      "draw": 0.3371,
      "t2_win": 0.3854
    },
    {
      "date": "2026-06-26",
      "round": "Matchday 16",
      "ground": "Vancouver",
      "team1": "New Zealand",
      "team2": "Belgium",
      "team1_flag": "🇳🇿",
      "team2_flag": "🇧🇪",
      "t1_win": 0.0911,
      "draw": 0.17,
      "t2_win": 0.739
    }
  ],
  "H": [
    {
      "date": "2026-06-15",
      "round": "Matchday 5",
      "ground": "Atlanta",
      "team1": "Spain",
      "team2": "Cape Verde",
      "team1_flag": "🇪🇸",
      "team2_flag": "🇨🇻",
      "t1_win": 0.7825,
      "draw": 0.1661,
      "t2_win": 0.0513
    },
    {
      "date": "2026-06-15",
      "round": "Matchday 5",
      "ground": "Miami (Miami Gardens)",
      "team1": "Saudi Arabia",
      "team2": "Uruguay",
      "team1_flag": "🇸🇦",
      "team2_flag": "🇺🇾",
      "t1_win": 0.1063,
      "draw": 0.2273,
      "t2_win": 0.6664
    },
    {
      "date": "2026-06-21",
      "round": "Matchday 11",
      "ground": "Atlanta",
      "team1": "Spain",
      "team2": "Saudi Arabia",
      "team1_flag": "🇪🇸",
      "team2_flag": "🇸🇦",
      "t1_win": 0.7603,
      "draw": 0.178,
      "t2_win": 0.0616
    },
    {
      "date": "2026-06-21",
      "round": "Matchday 11",
      "ground": "Miami (Miami Gardens)",
      "team1": "Uruguay",
      "team2": "Cape Verde",
      "team1_flag": "🇺🇾",
      "team2_flag": "🇨🇻",
      "t1_win": 0.7186,
      "draw": 0.2004,
      "t2_win": 0.081
    },
    {
      "date": "2026-06-26",
      "round": "Matchday 16",
      "ground": "Houston",
      "team1": "Cape Verde",
      "team2": "Saudi Arabia",
      "team1_flag": "🇨🇻",
      "team2_flag": "🇸🇦",
      "t1_win": 0.2391,
      "draw": 0.3388,
      "t2_win": 0.4221
    },
    {
      "date": "2026-06-26",
      "round": "Matchday 16",
      "ground": "Guadalajara (Zapopan)",
      "team1": "Uruguay",
      "team2": "Spain",
      "team1_flag": "🇺🇾",
      "team2_flag": "🇪🇸",
      "t1_win": 0.1812,
      "draw": 0.2629,
      "t2_win": 0.556
    }
  ],
  "I": [
    {
      "date": "2026-06-16",
      "round": "Matchday 6",
      "ground": "New York/New Jersey (East Rutherford)",
      "team1": "France",
      "team2": "Senegal",
      "team1_flag": "🇫🇷",
      "team2_flag": "🇸🇳",
      "t1_win": 0.6032,
      "draw": 0.252,
      "t2_win": 0.1448
    },
    {
      "date": "2026-06-16",
      "round": "Matchday 6",
      "ground": "Boston (Foxborough)",
      "team1": "Iraq",
      "team2": "Norway",
      "team1_flag": "🇮🇶",
      "team2_flag": "🇳🇴",
      "t1_win": 0.1543,
      "draw": 0.2426,
      "t2_win": 0.6031
    },
    {
      "date": "2026-06-22",
      "round": "Matchday 12",
      "ground": "Philadelphia",
      "team1": "France",
      "team2": "Iraq",
      "team1_flag": "🇫🇷",
      "team2_flag": "🇮🇶",
      "t1_win": 0.7346,
      "draw": 0.1849,
      "t2_win": 0.0804
    },
    {
      "date": "2026-06-22",
      "round": "Matchday 12",
      "ground": "New York/New Jersey (East Rutherford)",
      "team1": "Norway",
      "team2": "Senegal",
      "team1_flag": "🇳🇴",
      "team2_flag": "🇸🇳",
      "t1_win": 0.3919,
      "draw": 0.3082,
      "t2_win": 0.2999
    },
    {
      "date": "2026-06-26",
      "round": "Matchday 16",
      "ground": "Boston (Foxborough)",
      "team1": "Norway",
      "team2": "France",
      "team1_flag": "🇳🇴",
      "team2_flag": "🇫🇷",
      "t1_win": 0.1793,
      "draw": 0.2428,
      "t2_win": 0.5779
    },
    {
      "date": "2026-06-26",
      "round": "Matchday 16",
      "ground": "Toronto",
      "team1": "Senegal",
      "team2": "Iraq",
      "team1_flag": "🇸🇳",
      "team2_flag": "🇮🇶",
      "t1_win": 0.5196,
      "draw": 0.2992,
      "t2_win": 0.1812
    }
  ],
  "J": [
    {
      "date": "2026-06-16",
      "round": "Matchday 6",
      "ground": "Kansas City",
      "team1": "Argentina",
      "team2": "Algeria",
      "team1_flag": "🇦🇷",
      "team2_flag": "🇩🇿",
      "t1_win": 0.6804,
      "draw": 0.2103,
      "t2_win": 0.1093
    },
    {
      "date": "2026-06-16",
      "round": "Matchday 6",
      "ground": "San Francisco Bay Area (Santa Clara)",
      "team1": "Austria",
      "team2": "Jordan",
      "team1_flag": "🇦🇹",
      "team2_flag": "🇯🇴",
      "t1_win": 0.6533,
      "draw": 0.2167,
      "t2_win": 0.13
    },
    {
      "date": "2026-06-22",
      "round": "Matchday 12",
      "ground": "Dallas (Arlington)",
      "team1": "Argentina",
      "team2": "Austria",
      "team1_flag": "🇦🇷",
      "team2_flag": "🇦🇹",
      "t1_win": 0.6123,
      "draw": 0.2258,
      "t2_win": 0.1619
    },
    {
      "date": "2026-06-22",
      "round": "Matchday 12",
      "ground": "San Francisco Bay Area (Santa Clara)",
      "team1": "Jordan",
      "team2": "Algeria",
      "team1_flag": "🇯🇴",
      "team2_flag": "🇩🇿",
      "t1_win": 0.1793,
      "draw": 0.2855,
      "t2_win": 0.5352
    },
    {
      "date": "2026-06-27",
      "round": "Matchday 17",
      "ground": "Kansas City",
      "team1": "Algeria",
      "team2": "Austria",
      "team1_flag": "🇩🇿",
      "team2_flag": "🇦🇹",
      "t1_win": 0.2581,
      "draw": 0.3067,
      "t2_win": 0.4352
    },
    {
      "date": "2026-06-27",
      "round": "Matchday 17",
      "ground": "Dallas (Arlington)",
      "team1": "Jordan",
      "team2": "Argentina",
      "team1_flag": "🇯🇴",
      "team2_flag": "🇦🇷",
      "t1_win": 0.057,
      "draw": 0.1536,
      "t2_win": 0.7895
    }
  ],
  "K": [
    {
      "date": "2026-06-17",
      "round": "Matchday 7",
      "ground": "Houston",
      "team1": "Portugal",
      "team2": "DR Congo",
      "team1_flag": "🇵🇹",
      "team2_flag": "🇨🇩",
      "t1_win": 0.6849,
      "draw": 0.21,
      "t2_win": 0.1051
    },
    {
      "date": "2026-06-17",
      "round": "Matchday 7",
      "ground": "Mexico City",
      "team1": "Uzbekistan",
      "team2": "Colombia",
      "team1_flag": "🇺🇿",
      "team2_flag": "🇨🇴",
      "t1_win": 0.1385,
      "draw": 0.2389,
      "t2_win": 0.6226
    },
    {
      "date": "2026-06-23",
      "round": "Matchday 13",
      "ground": "Houston",
      "team1": "Portugal",
      "team2": "Uzbekistan",
      "team1_flag": "🇵🇹",
      "team2_flag": "🇺🇿",
      "t1_win": 0.7097,
      "draw": 0.1909,
      "t2_win": 0.0994
    },
    {
      "date": "2026-06-23",
      "round": "Matchday 13",
      "ground": "Guadalajara (Zapopan)",
      "team1": "Colombia",
      "team2": "DR Congo",
      "team1_flag": "🇨🇴",
      "team2_flag": "🇨🇩",
      "t1_win": 0.6153,
      "draw": 0.2437,
      "t2_win": 0.141
    },
    {
      "date": "2026-06-27",
      "round": "Matchday 17",
      "ground": "Miami (Miami Gardens)",
      "team1": "Colombia",
      "team2": "Portugal",
      "team1_flag": "🇨🇴",
      "team2_flag": "🇵🇹",
      "t1_win": 0.2927,
      "draw": 0.3205,
      "t2_win": 0.3868
    },
    {
      "date": "2026-06-27",
      "round": "Matchday 17",
      "ground": "Atlanta",
      "team1": "DR Congo",
      "team2": "Uzbekistan",
      "team1_flag": "🇨🇩",
      "team2_flag": "🇺🇿",
      "t1_win": 0.343,
      "draw": 0.3037,
      "t2_win": 0.3533
    }
  ],
  "L": [
    {
      "date": "2026-06-17",
      "round": "Matchday 7",
      "ground": "Dallas (Arlington)",
      "team1": "England",
      "team2": "Croatia",
      "team1_flag": "🏴󠁧󠁢󠁥󠁮󠁧󠁿",
      "team2_flag": "🇭🇷",
      "t1_win": 0.5104,
      "draw": 0.2875,
      "t2_win": 0.2022
    },
    {
      "date": "2026-06-17",
      "round": "Matchday 7",
      "ground": "Toronto",
      "team1": "Ghana",
      "team2": "Panama",
      "team1_flag": "🇬🇭",
      "team2_flag": "🇵🇦",
      "t1_win": 0.4056,
      "draw": 0.2955,
      "t2_win": 0.2989
    },
    {
      "date": "2026-06-23",
      "round": "Matchday 13",
      "ground": "Boston (Foxborough)",
      "team1": "England",
      "team2": "Ghana",
      "team1_flag": "🏴󠁧󠁢󠁥󠁮󠁧󠁿",
      "team2_flag": "🇬🇭",
      "t1_win": 0.6969,
      "draw": 0.2079,
      "t2_win": 0.0952
    },
    {
      "date": "2026-06-23",
      "round": "Matchday 13",
      "ground": "Toronto",
      "team1": "Panama",
      "team2": "Croatia",
      "team1_flag": "🇵🇦",
      "team2_flag": "🇭🇷",
      "t1_win": 0.1197,
      "draw": 0.2152,
      "t2_win": 0.6652
    },
    {
      "date": "2026-06-27",
      "round": "Matchday 17",
      "ground": "New York/New Jersey (East Rutherford)",
      "team1": "Panama",
      "team2": "England",
      "team1_flag": "🇵🇦",
      "team2_flag": "🏴󠁧󠁢󠁥󠁮󠁧󠁿",
      "t1_win": 0.0645,
      "draw": 0.1379,
      "t2_win": 0.7976
    },
    {
      "date": "2026-06-27",
      "round": "Matchday 17",
      "ground": "Philadelphia",
      "team1": "Croatia",
      "team2": "Ghana",
      "team1_flag": "🇭🇷",
      "team2_flag": "🇬🇭",
      "t1_win": 0.5925,
      "draw": 0.26,
      "t2_win": 0.1475
    }
  ]
}